sflux/__init__.py
sflux/client.py
sflux/measurement.py
sflux/utils.py
sflux-0.0.35.dist-info/licenses/LICENSE
sflux-0.0.35.dist-info/METADATA
sflux-0.0.35.dist-info/WHEEL
sflux-0.0.35.dist-info/top_level.txt
sflux-0.0.35.dist-info/RECORD
