Metadata-Version: 2.4
Name: sflux
Version: 0.0.35
Summary: A simple python interface for InfluxDB2.0
Home-page: https://github.com/perrytec/sflux.git
Author: perrytec
Author-email: hello@perry.sg
Classifier: Programming Language :: Python :: 3
Classifier: License :: OSI Approved :: MIT License
Classifier: Operating System :: OS Independent
Requires-Python: >=3.8
License-File: LICENSE
Requires-Dist: influxdb_client
Requires-Dist: ciso8601
Dynamic: license-file
